pyloom_asr/__init__.py
pyloom_asr/pyloom_asr.py
pyloom_asr-0.0.1.dist-info/LICENSE
pyloom_asr-0.0.1.dist-info/METADATA
pyloom_asr-0.0.1.dist-info/WHEEL
pyloom_asr-0.0.1.dist-info/top_level.txt
pyloom_asr-0.0.1.dist-info/RECORD
